glog/__init__.py
glog/context_logger.py
glog/level.py
glog/logger.py
glog/options.py
glog/run_tests.sh
glog/examples/basic_example.py
glog/examples/context_example.py
glog/examples/glog_format_example.py
glog/examples/simple_usage.py
glog/tests/test_context_logger.py
glog/tests/test_logger.py
glog_python-1.0.1.dist-info/METADATA
glog_python-1.0.1.dist-info/WHEEL
glog_python-1.0.1.dist-info/top_level.txt
glog_python-1.0.1.dist-info/RECORD
