Metadata-Version: 2.4
Name: glog-python
Version: 1.0.1
Summary: Python logging library compatible with Go glog format
Home-page: https://github.com/gw123/glog
Author: gw123
Author-email: 
License: MIT
Project-URL: Homepage, https://github.com/gw123/glog
Project-URL: Repository, https://github.com/gw123/glog
Project-URL: Bug Reports, https://github.com/gw123/glog/issues
Keywords: logging,glog,structured-logging,context-logging,trace-id
Classifier: Development Status :: 4 - Beta
Classifier: Intended Audience :: Developers
Classifier: Topic :: Software Development :: Libraries :: Python Modules
Classifier: Topic :: System :: Logging
Classifier: License :: OSI Approved :: MIT License
Classifier: Programming Language :: Python :: 3
Classifier: Programming Language :: Python :: 3.7
Classifier: Programming Language :: Python :: 3.8
Classifier: Programming Language :: Python :: 3.9
Classifier: Programming Language :: Python :: 3.10
Classifier: Programming Language :: Python :: 3.11
Classifier: Programming Language :: Python :: 3.12
Classifier: Operating System :: OS Independent
Requires-Python: >=3.7
Dynamic: home-page
Dynamic: requires-python
